kyber/__init__.py
kyber/aes256_ctr_drbg.py
kyber/baby-kyber.py
kyber/benchmark_kyber.py
kyber/kyber.py
kyber/modules.py
kyber/ntt_helper.py
kyber/polynomials.py
kyber/test_kyber.py
kyber/utils.py
kyber_py-0.2.2.dist-info/LICENSE
kyber_py-0.2.2.dist-info/METADATA
kyber_py-0.2.2.dist-info/WHEEL
kyber_py-0.2.2.dist-info/RECORD
