Metadata-Version: 2.1
Name: kyber-py
Version: 0.2.2
Summary: Implementation of the kyber crystal algorithm made by https://github.com/jack4818/kyber-py
License: MIT
Author: Marc Partensky
Author-email: marc.partensky@gmail.com
Requires-Python: >=3.10,<4.0
Classifier: License :: OSI Approved :: MIT License
Classifier: Programming Language :: Python :: 3
Classifier: Programming Language :: Python :: 3.10
Classifier: Programming Language :: Python :: 3.11
Requires-Dist: pycryptodome (==3.14.1)
